README.md
pyproject.toml
setup.cfg
setup.py
decoupler/__init__.py
decoupler/admin.py
decoupler/apps.py
decoupler/models.py
decoupler/tests.py
decoupler/views.py
decoupler/migrations/__init__.py
django_model_decoupler.egg-info/PKG-INFO
django_model_decoupler.egg-info/SOURCES.txt
django_model_decoupler.egg-info/dependency_links.txt
django_model_decoupler.egg-info/requires.txt
django_model_decoupler.egg-info/top_level.txt