Metadata-Version: 2.1
Name: django-model-decoupler
Version: 0.0.2
Summary: A model decoupler for Django
Home-page: https://github.com/genadijrazdorov/django-model-decoupler
Author: Genadij Razdorov
Author-email: genadijrazdorov@gmail.com
License: MIT
Project-URL: Bug Tracker, https://github.com/genadijrazdorov/django-model-decoupler/issues
Platform: UNKNOWN
Classifier: Programming Language :: Python :: 3
Classifier: License :: OSI Approved :: MIT License
Classifier: Operating System :: OS Independent
Requires-Python: >=3.6
